{
    "limiter_enabled": true,
    "books": {
        "1922427586": {
            "url": "https://www.amazon.com/Remembering-Other-Stories-Lewis-Woolston/dp/1922427586",
            "asin": "1922427586",
            "title": "Remembering the Dead and Other Stories",
            "author": "Lewis Woolston",
            "cover_url": "https://m.media-amazon.com/images/I/611yH2-BvNL._SY522_.jpg",
            "bsr": 5364459,
            "last_checked": "2025-02-28T00:01:58.155Z",
            "status": "active",
            "last_updated": "2025-02-28T00:01:58.155Z"
        },
        "1925536882": {
            "url": "https://www.amazon.com/Last-Free-Man-Other-Stories/dp/1925536882",
            "asin": "1925536882",
            "title": "The Last Free Man and Other Stories",
            "author": "Lewis Woolston",
            "cover_url": "https://m.media-amazon.com/images/I/71TPgME7cpL._SY522_.jpg",
            "bsr": 4820413,
            "last_checked": "2025-02-28T00:00:26.654Z",
            "status": "active",
            "last_updated": "2025-02-28T00:00:26.655Z"
        },
        "1957599022": {
            "url": "https://www.amazon.com/dp/1957599022",
            "asin": "1957599022",
            "title": "Faceless",
            "author": "James Krake",
            "cover_url": "https://m.media-amazon.com/images/I/61hIGnVOy4L._SY522_.jpg",
            "bsr": 4168592,
            "last_checked": "2025-02-28T00:01:06.436Z",
            "status": "active",
            "last_updated": "2025-02-28T00:01:06.436Z"
        },
        "1957599030": {
            "url": "https://www.amazon.com/dp/1957599030",
            "asin": "1957599030",
            "title": "Gamma Coin",
            "author": "James Krake",
            "cover_url": "https://m.media-amazon.com/images/I/710761zZlLL._SY522_.jpg",
            "bsr": 7253208,
            "last_checked": "2025-02-28T00:01:13.163Z",
            "status": "active",
            "last_updated": "2025-02-28T00:01:13.163Z"
        },
        "1957599065": {
            "url": "https://www.amazon.com/dp/1957599065",
            "asin": "1957599065",
            "title": "Ship of Fuls",
            "author": "James Krake",
            "cover_url": "https://m.media-amazon.com/images/I/71riYYAiG5L._SY522_.jpg",
            "bsr": 4846869,
            "last_checked": "2025-02-28T00:01:24.129Z",
            "status": "active",
            "last_updated": "2025-02-28T00:01:24.129Z"
        },
        "B0DRT5T927": {
            "url": "https://www.amazon.com/dp/B0DRT5T927",
            "asin": "B0DRT5T927",
            "title": "Harry Potter Trivia Book",
            "author": "Amanda Hopkins",
            "cover_url": "https://m.media-amazon.com/images/I/71F562RlHAL._SY522_.jpg",
            "bsr": 2171430,
            "last_checked": "2025-02-28T00:01:45.716Z",
            "status": "active",
            "last_updated": "2025-02-28T00:01:45.716Z"
        },
        "B0B9265BPY": {
            "url": "https://www.amazon.com/Savage-Green-Zulu-Alitspa/dp/B0B9265BPY",
            "asin": "B0B9265BPY",
            "title": "The Savage Green",
            "author": "Zulu Alitspa",
            "cover_url": "https://m.media-amazon.com/images/I/71TbYqEmBxL._SY522_.jpg",
            "bsr": 2751570,
            "last_checked": "2025-02-28T00:01:51.885Z",
            "status": "active",
            "last_updated": "2025-02-28T00:01:51.885Z"
        },
        "B0DCS1X54Z": {
            "url": "https://www.amazon.com/SILKWORM-Ogden-Nesmer/dp/B0DCS1X54Z",
            "asin": "B0DCS1X54Z",
            "title": "SILKWORM",
            "author": "Ogden Nesmer",
            "cover_url": "https://m.media-amazon.com/images/I/71g7j2pCt5L._SY522_.jpg",
            "bsr": 4091778,
            "last_checked": "2025-02-28T00:02:08.425Z",
            "status": "active",
            "last_updated": "2025-02-28T00:02:08.425Z"
        },
        "B0CJLCZVCG": {
            "url": "https://www.amazon.com/INCEL-Novel-ARX-Han/dp/B0CJLCZVCG",
            "asin": "B0CJLCZVCG",
            "title": "INCEL",
            "author": "ARX-Han",
            "cover_url": "https://m.media-amazon.com/images/I/81DwGA83SgL._SY522_.jpg",
            "bsr": 687902,
            "last_checked": "2025-02-28T00:02:15.222Z",
            "status": "active",
            "last_updated": "2025-02-28T00:02:15.222Z"
        },
        "B0CWCF7J13": {
            "url": "https://www.amazon.com/Improvidence-David-Herod/dp/B0CWCF7J13",
            "asin": "B0CWCF7J13",
            "title": "Improvidence",
            "author": "David Herod",
            "cover_url": "https://m.media-amazon.com/images/I/61EhziObbuL._SY522_.jpg",
            "bsr": 1087599,
            "last_checked": "2025-02-28T00:02:22.064Z",
            "status": "active",
            "last_updated": "2025-02-28T00:02:22.064Z"
        },
        "B09MJBNL7X": {
            "url": "https://www.amazon.com/Eggplant-Ogden-Nesmer/dp/B09MJBNL7X",
            "asin": "B09MJBNL7X",
            "title": "Eggplant",
            "author": "Ogden Nesmer",
            "cover_url": "https://m.media-amazon.com/images/I/71sQQGkR2TL._SY522_.jpg",
            "bsr": 3355914,
            "last_checked": "2025-02-28T00:02:33.187Z",
            "status": "active",
            "last_updated": "2025-02-28T00:02:33.187Z"
        },
        "B0BMJMP3GK": {
            "url": "https://www.amazon.com/Pray-Hungry-God-Ogden-Nesmer/dp/B0BMJMP3GK",
            "asin": "B0BMJMP3GK",
            "title": "I Pray to the Hungry God",
            "author": "Ogden Nesmer",
            "cover_url": "https://m.media-amazon.com/images/I/619K8gFdVVL._SY522_.jpg",
            "bsr": 4471029,
            "last_checked": "2025-02-28T00:02:39.157Z",
            "status": "active",
            "last_updated": "2025-02-28T00:02:39.157Z"
        },
        "B0B6LBBJ3S": {
            "url": "https://www.amazon.com/Modem-Waves-Zulu-Alitspa/dp/B0B6LBBJ3S",
            "asin": "B0B6LBBJ3S",
            "title": "Modem Waves",
            "author": "Zulu Alitspa",
            "cover_url": "https://m.media-amazon.com/images/I/71DxACNamhL._SY522_.jpg",
            "bsr": 5175498,
            "last_checked": "2025-02-27T23:59:31.607Z",
            "status": "active",
            "last_updated": "2025-02-27T23:59:31.607Z"
        },
        "B0BTJ6JV1D": {
            "url": "https://www.amazon.com/Panther-Pride-Zulu-Alitspa/dp/B0BTJ6JV1D",
            "asin": "B0BTJ6JV1D",
            "title": "Panther Pride",
            "author": "Zulu Alitspa",
            "cover_url": "https://m.media-amazon.com/images/I/71+NPJOyl3L._SY522_.jpg",
            "bsr": 6560484,
            "last_checked": "2025-02-27T23:59:38.398Z",
            "status": "active",
            "last_updated": "2025-02-27T23:59:38.398Z"
        },
        "B0BW31G7MG": {
            "url": "https://www.amazon.com/Cephalopology-narrative-recounting-humanitys-intelligence/dp/B0BW31G7MG",
            "asin": "B0BW31G7MG",
            "title": "Cephalopology",
            "author": "Zulu Alitspa",
            "cover_url": "https://m.media-amazon.com/images/I/717tTvRYggL._SY522_.jpg",
            "bsr": 3982174,
            "last_checked": "2025-02-27T23:59:48.674Z",
            "status": "active",
            "last_updated": "2025-02-27T23:59:48.674Z"
        },
        "B0BW32CX2G": {
            "url": "https://www.amazon.com/Mixtape-Hyperborea-Adem-Luz-Rienspects/dp/B0BW32CX2G",
            "asin": "B0BW32CX2G",
            "title": "Mixtape Hyperborea",
            "author": "Adem Luz Rienspects",
            "cover_url": "https://m.media-amazon.com/images/I/71Z6dEF6rBL._SY522_.jpg",
            "bsr": 344840,
            "last_checked": "2025-02-27T23:59:55.448Z",
            "status": "active",
            "last_updated": "2025-02-27T23:59:55.448Z"
        },
        "B0DLGLKGFB": {
            "url": "https://www.amazon.com/Shards-City-Robert-James-Cross/dp/B0DLGLKGFB",
            "asin": "B0DLGLKGFB",
            "title": "Shards",
            "author": "Robert James Cross",
            "cover_url": "https://m.media-amazon.com/images/I/41Nr6CfHZUL._SY522_.jpg",
            "bsr": 9211996,
            "last_checked": "2025-02-28T00:00:03.509Z",
            "status": "active",
            "last_updated": "2025-02-28T00:00:03.509Z"
        },
        "B0BYRNM6Z5": {
            "url": "https://www.amazon.com/dp/B0BYRNM6Z5",
            "asin": "B0BYRNM6Z5",
            "title": "Chicken World",
            "author": "K. R. Hartley",
            "cover_url": "https://m.media-amazon.com/images/I/61SRpyydboL._SY522_.jpg",
            "bsr": 5107856,
            "last_checked": "2025-02-28T00:00:13.527Z",
            "status": "active",
            "last_updated": "2025-02-28T00:00:13.527Z"
        },
        "B0B477N8ZG": {
            "url": "https://www.amazon.com/People-Mover-John-David-Card/dp/B0B477N8ZG",
            "asin": "B0B477N8ZG",
            "title": "People Mover",
            "author": "John David Card",
            "cover_url": "https://m.media-amazon.com/images/I/715C3sWJR6L._SY522_.jpg",
            "bsr": 10920379,
            "last_checked": "2025-02-28T00:00:20.297Z",
            "status": "active",
            "last_updated": "2025-02-28T00:00:20.297Z"
        },
        "B09JJFF82K": {
            "url": "https://www.amazon.com/Book-Void-Sun-Lion-Serpent-feet-Christ/dp/B09JJFF82K",
            "asin": "B09JJFF82K",
            "title": "The Book of the Void-Sun and the Lion-Serpent at the feet of Christ",
            "author": "Frater Asemlen",
            "cover_url": "https://m.media-amazon.com/images/I/719juUMCMrL._SY522_.jpg",
            "bsr": 4978534,
            "last_checked": "2025-02-28T00:00:43.275Z",
            "status": "active",
            "last_updated": "2025-02-28T00:00:43.275Z"
        },
        "195759912X": {
            "url": "https://www.amazon.com/dp/195759912X",
            "asin": "195759912X",
            "title": "Take Down Request",
            "author": "James Krake",
            "cover_url": "https://m.media-amazon.com/images/I/61May26C-iL._SY522_.jpg",
            "bsr": 6672824,
            "last_checked": "2025-02-28T00:00:59.620Z",
            "status": "active",
            "last_updated": "2025-02-28T00:00:59.620Z"
        }
    },
    "last_update": "2025-02-27T23:40:43.166Z",
    "cycle_status": {
        "state": "running",
        "started_at": "2025-02-28T00:01:43.191Z"
    },
    "scraping_progress": {
        "current": 8,
        "total": 44,
        "successful": 0
    }
}